Metadata-Version: 2.4
Name: livekit-protocol
Version: 1.0.0
Summary: Python protocol stubs for LiveKit
Home-page: https://github.com/livekit/python-sdks
License: Apache-2.0
Project-URL: Documentation, https://docs.livekit.io
Project-URL: Website, https://livekit.io/
Project-URL: Source, https://github.com/livekit/python-sdks/
Keywords: webrtc,realtime,audio,video,livekit
Classifier: Intended Audience :: Developers
Classifier: Programming Language :: Python :: 3
Classifier: Programming Language :: Python :: 3.7
Classifier: Programming Language :: Python :: 3.8
Classifier: Programming Language :: Python :: 3.9
Classifier: Programming Language :: Python :: 3.10
Classifier: Programming Language :: Python :: 3 :: Only
Requires-Python: >=3.7.0
Requires-Dist: protobuf>=3
Requires-Dist: types-protobuf<5,>=4
Dynamic: classifier
Dynamic: description
Dynamic: description-content-type
Dynamic: home-page
Dynamic: keywords
Dynamic: license
Dynamic: project-url
Dynamic: requires-dist
Dynamic: requires-python
Dynamic: summary
